csvapi/__init__.py
csvapi/cli.py
csvapi/errors.py
csvapi/exportview.py
csvapi/parser.py
csvapi/parseview.py
csvapi/profiling.py
csvapi/security.py
csvapi/tableview.py
csvapi/type_tester.py
csvapi/uploadview.py
csvapi/utils.py
csvapi/webservice.py
csvapi-2.2.0.dist-info/entry_points.txt
csvapi-2.2.0.dist-info/LICENSE
csvapi-2.2.0.dist-info/WHEEL
csvapi-2.2.0.dist-info/METADATA
csvapi-2.2.0.dist-info/RECORD
