Metadata-Version: 2.1
Name: csvapi
Version: 2.2.0
Summary: An instant JSON API for your CSV
License: MIT
Author: Opendatateam
Author-email: opendatateam@data.gouv.fr
Requires-Python: >=3.9,<4
Classifier: License :: OSI Approved :: MIT License
Classifier: Programming Language :: Python :: 3
Classifier: Programming Language :: Python :: 3.9
Classifier: Programming Language :: Python :: 3.10
Classifier: Programming Language :: Python :: 3.11
Requires-Dist: Quart (>=0.18.0,<0.19.0)
Requires-Dist: agate (>=1.6.3,<1.7.0)
Requires-Dist: agate-excel (>=0.2.5,<0.3.0)
Requires-Dist: agate-sql (>=0.5.8,<0.6.0)
Requires-Dist: aiohttp (>=3.8.1,<3.9.0)
Requires-Dist: aiosqlite (>=0.17.0,<0.18.0)
Requires-Dist: boto3 (>=1.24.66,<1.25.0)
Requires-Dist: cchardet (>=2.1.7,<2.2.0)
Requires-Dist: click (>=8.1.3,<8.2.0)
Requires-Dist: click_default_group (>=1.2.2,<1.3.0)
Requires-Dist: csv-detective (>=0.4.6,<0.5.0)
Requires-Dist: pandas (>=1.4.4,<1.5.0)
Requires-Dist: pandas-profiling (>=3.2.0,<3.3.0)
Requires-Dist: python-stdnum (>=1.17,<1.18)
Requires-Dist: quart-cors (>=0.5.0,<0.6.0)
Requires-Dist: requests (>=2.28.1,<2.29.0)
Requires-Dist: sentry-sdk (>=1.9.8,<1.10.0)
Requires-Dist: validators (>=0.20.0,<0.21.0)
